[
    {
        "path": "404.html",
        "type": "file",
        "md5": "d18f0017b838540870acadf1f8a69867"
    },
    {
        "path": "assets",
        "type": "directory",
        "md5": false
    },
    {
        "path": "assets/css",
        "type": "directory",
        "md5": false
    },
    {
        "path": "/assets/css/editor.css",
        "type": "file",
        "md5": "4202808df745f2ac7ab250606fa0d272"
    },
    {
        "path": "/assets/css/main.css",
        "type": "file",
        "md5": "fa238f48f9a2ab93b0c59a116e831bca"
    },
    {
        "path": "/assets/css/style.css",
        "type": "file",
        "md5": "11bee19e86e8eda2cf9a60efd975666d"
    },
    {
        "path": "assets/dynamic",
        "type": "directory",
        "md5": false
    },
    {
        "path": "assets/js",
        "type": "directory",
        "md5": false
    },
    {
        "path": "/assets/js/scripts.js",
        "type": "file",
        "md5": "e9e5c3efbaa696d1490988cf5b30e23b"
    },
    {
        "path": "/assets/js/scripts.min.js",
        "type": "file",
        "md5": "700105c316933a8202041b6415abb233"
    },
    {
        "path": "/assets/js/svg-fix.js",
        "type": "file",
        "md5": "9b7d020c55e2b4f77ab40c97f88f9ff4"
    },
    {
        "path": "/assets/js/svg-map.js",
        "type": "file",
        "md5": "ff4392540fcf4c3d3f5e03806e112816"
    },
    {
        "path": "assets/svg",
        "type": "directory",
        "md5": false
    },
    {
        "path": "/assets/svg/svg-map.svg",
        "type": "file",
        "md5": "cf04dfd5c3cc64e0be44692fe7d976a6"
    },
    {
        "path": "authors",
        "type": "directory",
        "md5": false
    },
    {
        "path": "authors/heba",
        "type": "directory",
        "md5": false
    },
    {
        "path": "/authors/heba/index.html",
        "type": "file",
        "md5": "b8905948d502003509fbb967c8de9413"
    },
    {
        "path": "feed.json",
        "type": "file",
        "md5": "85d0e95a053b965b8c9060582c5f53cc"
    },
    {
        "path": "feed.xml",
        "type": "file",
        "md5": "a816551542e736af28110887264b2dbc"
    },
    {
        "path": "hmy-ltnzyf-ldwry-maa-shrk-tnzyf-fy-lshrq",
        "type": "directory",
        "md5": false
    },
    {
        "path": "/hmy-ltnzyf-ldwry-maa-shrk-tnzyf-fy-lshrq/index.html",
        "type": "file",
        "md5": "cc5dea607b29ea981f94cd83f49b8785"
    },
    {
        "path": "index.html",
        "type": "file",
        "md5": "f46503afb1011071d564c0d38dc0c9ca"
    },
    {
        "path": "mt~-thtj-l~-shrk-tnzyf-fy-lshrq",
        "type": "directory",
        "md5": false
    },
    {
        "path": "/mt~-thtj-l~-shrk-tnzyf-fy-lshrq/index.html",
        "type": "file",
        "md5": "371c7632518eeaa03589314ed075aaa4"
    },
    {
        "path": "robots.txt",
        "type": "file",
        "md5": "28b161c920d320247479e49ed1576f09"
    },
    {
        "path": "shrk-tnzyf-fy-lshrq",
        "type": "directory",
        "md5": false
    },
    {
        "path": "/shrk-tnzyf-fy-lshrq/index.html",
        "type": "file",
        "md5": "8829d81e44ff888b99981c2a80012ef3"
    },
    {
        "path": "sitemap.xml",
        "type": "file",
        "md5": "b016997fecc152f8b0c54ccac82cf714"
    },
    {
        "path": "sitemap.xsl",
        "type": "file",
        "md5": "03c2f9a7fdcc46ff05c435907614a0b8"
    },
    {
        "path": "tags",
        "type": "directory",
        "md5": false
    },
    {
        "path": "/tags/index.html",
        "type": "file",
        "md5": "45a14c3612b2d832223f8787a75ef572"
    }
]